okridge/__init__.py
okridge/node.py
okridge/solvers.py
okridge/tree.py
okridge/utils.py
okridge-0.1.1.dist-info/LICENSE
okridge-0.1.1.dist-info/METADATA
okridge-0.1.1.dist-info/WHEEL
okridge-0.1.1.dist-info/RECORD
