Metadata-Version: 2.1
Name: okridge
Version: 0.1.1
Summary: A packge for solving k-sparse ridge regression certifiably!
License: BSD 3-Clause
Author: Jiachang Liu
Requires-Python: >=3.9,<3.13
Classifier: License :: Other/Proprietary License
Classifier: Programming Language :: Python :: 3
Classifier: Programming Language :: Python :: 3.9
Classifier: Programming Language :: Python :: 3.10
Classifier: Programming Language :: Python :: 3.11
Classifier: Programming Language :: Python :: 3.12
Requires-Dist: numpy (>=1.26.1,<2.0.0)
Requires-Dist: psutil (>=5.9.6,<6.0.0)
Requires-Dist: scikit-learn (>=1.3.2,<2.0.0)
Requires-Dist: scipy (>=1.11.3,<2.0.0)
